svg2pptx/__init__.py
svg2pptx/__main__.py
svg2pptx/cli.py
svg2pptx/config.py
svg2pptx/converter.py
svg2pptx/geometry/__init__.py
svg2pptx/geometry/curves.py
svg2pptx/geometry/transforms.py
svg2pptx/geometry/units.py
svg2pptx/parser/__init__.py
svg2pptx/parser/paths.py
svg2pptx/parser/shapes.py
svg2pptx/parser/styles.py
svg2pptx/parser/svg_parser.py
svg2pptx/parser/transforms.py
svg2pptx/pptx_writer/__init__.py
svg2pptx/pptx_writer/freeform.py
svg2pptx/pptx_writer/groups.py
svg2pptx/pptx_writer/shapes.py
svg2pptx/pptx_writer/text.py
svg2pptx-1.0.2.dist-info/METADATA
svg2pptx-1.0.2.dist-info/WHEEL
svg2pptx-1.0.2.dist-info/entry_points.txt
svg2pptx-1.0.2.dist-info/top_level.txt
svg2pptx-1.0.2.dist-info/RECORD
