Metadata-Version: 2.4
Name: svg2pptx
Version: 1.0.2
Summary: Convert SVG files to native, editable PowerPoint shapes
Author: Rachid BENOUINI
License: MIT
Project-URL: Homepage, https://github.com/benouinirachid/svg2pptx
Project-URL: Repository, https://github.com/benouinirachid/svg2pptx
Keywords: svg,powerpoint,pptx,converter,vector,graphics
Classifier: Development Status :: 3 - Alpha
Classifier: Intended Audience :: Developers
Classifier: License :: OSI Approved :: MIT License
Classifier: Programming Language :: Python :: 3
Classifier: Programming Language :: Python :: 3.9
Classifier: Programming Language :: Python :: 3.10
Classifier: Programming Language :: Python :: 3.11
Classifier: Programming Language :: Python :: 3.12
Classifier: Topic :: Multimedia :: Graphics :: Graphics Conversion
Classifier: Topic :: Office/Business :: Office Suites
Requires-Python: >=3.9
Requires-Dist: python-pptx>=0.6.21
Requires-Dist: svgpathtools>=1.6.1
Provides-Extra: dev
Requires-Dist: pytest>=7.0; extra == "dev"
Requires-Dist: pytest-cov>=4.0; extra == "dev"
